vbumper/__init__.py
vbumper/bump_type.py
vbumper/git.py
vbumper/main.py
vbumper/vbumper.py
vbumper/versions.py
vbumper-0.1.1.dist-info/METADATA
vbumper-0.1.1.dist-info/WHEEL
vbumper-0.1.1.dist-info/entry_points.txt
vbumper-0.1.1.dist-info/RECORD
