Metadata-Version: 2.3
Name: vbumper
Version: 0.1.1
Summary: Comprehensive version bumping for Python projects
Author: Danny Stewart
Author-email: danny@stewart.cc
Requires-Python: >=3.12
Classifier: Programming Language :: Python :: 3
Classifier: Programming Language :: Python :: 3.12
Classifier: Programming Language :: Python :: 3.13
Requires-Dist: dsbase (>=0.2.2,<0.3.0)
Project-URL: Repository, https://github.com/dannystewart/vbumper
